<?xml version="1.0" encoding="UTF-8"?>
<!DOCTYPE mapper PUBLIC "-//mybatis.org//DTD Mapper 3.0//EN" "http://mybatis.org/dtd/mybatis-3-mapper.dtd">
<mapper namespace="biz.dao.IRemakeLogDao">
  <resultMap id="BaseResultMap" type="biz.domain.RemakeLog">
    <id column="remake_log_id" jdbcType="INTEGER" property="remakeLogId" />
    <result column="remake_log" jdbcType="VARCHAR" property="remakeLog" />
    <result column="create_time" jdbcType="TIMESTAMP" property="createTime" />
    <result column="motify_time" jdbcType="TIMESTAMP" property="motifyTime" />
  </resultMap>
  <sql id="Base_Column_List">
    remake_log_id, remake_log, create_time, motify_time
  </sql>
  <select id="selectByPrimaryKey" parameterType="java.lang.Integer" resultMap="BaseResultMap">
    select 
    <include refid="Base_Column_List" />
    from remake_log
    where remake_log_id = #{remakeLogId,jdbcType=INTEGER}
  </select>
  <delete id="deleteByPrimaryKey" parameterType="java.lang.Integer">
    delete from remake_log
    where remake_log_id = #{remakeLogId,jdbcType=INTEGER}
  </delete>
  <insert id="insert" parameterType="biz.domain.RemakeLog">
    insert into remake_log (remake_log_id, remake_log, create_time, 
      motify_time)
    values (#{remakeLogId,jdbcType=INTEGER}, #{remakeLog,jdbcType=VARCHAR}, #{createTime,jdbcType=TIMESTAMP}, 
      #{motifyTime,jdbcType=TIMESTAMP})
  </insert>
  <insert id="insertSelective" parameterType="biz.domain.RemakeLog">
    insert into remake_log
    <trim prefix="(" suffix=")" suffixOverrides=",">
      <if test="remakeLogId != null">
        remake_log_id,
      </if>
      <if test="remakeLog != null">
        remake_log,
      </if>
      <if test="createTime != null">
        create_time,
      </if>
      <if test="motifyTime != null">
        motify_time,
      </if>
    </trim>
    <trim prefix="values (" suffix=")" suffixOverrides=",">
      <if test="remakeLogId != null">
        #{remakeLogId,jdbcType=INTEGER},
      </if>
      <if test="remakeLog != null">
        #{remakeLog,jdbcType=VARCHAR},
      </if>
      <if test="createTime != null">
        #{createTime,jdbcType=TIMESTAMP},
      </if>
      <if test="motifyTime != null">
        #{motifyTime,jdbcType=TIMESTAMP},
      </if>
    </trim>
  </insert>
  <update id="updateByPrimaryKeySelective" parameterType="biz.domain.RemakeLog">
    update remake_log
    <set>
      <if test="remakeLog != null">
        remake_log = #{remakeLog,jdbcType=VARCHAR},
      </if>
      <if test="createTime != null">
        create_time = #{createTime,jdbcType=TIMESTAMP},
      </if>
      <if test="motifyTime != null">
        motify_time = #{motifyTime,jdbcType=TIMESTAMP},
      </if>
    </set>
    where remake_log_id = #{remakeLogId,jdbcType=INTEGER}
  </update>
  <update id="updateByPrimaryKey" parameterType="biz.domain.RemakeLog">
    update remake_log
    set remake_log = #{remakeLog,jdbcType=VARCHAR},
      create_time = #{createTime,jdbcType=TIMESTAMP},
      motify_time = #{motifyTime,jdbcType=TIMESTAMP}
    where remake_log_id = #{remakeLogId,jdbcType=INTEGER}
  </update>
</mapper>